pymugi/__init__.py
pymugi/mugi.py
pymugi-0.1.2.dist-info/LICENSE
pymugi-0.1.2.dist-info/METADATA
pymugi-0.1.2.dist-info/WHEEL
pymugi-0.1.2.dist-info/top_level.txt
pymugi-0.1.2.dist-info/zip-safe
pymugi-0.1.2.dist-info/RECORD
